volvisualizer/__init__.py
volvisualizer/graph.py
volvisualizer/volatility.py
volvisualizer-1.2.4.dist-info/licenses/LICENSE
volvisualizer-1.2.4.dist-info/METADATA
volvisualizer-1.2.4.dist-info/WHEEL
volvisualizer-1.2.4.dist-info/top_level.txt
volvisualizer-1.2.4.dist-info/RECORD
