Metadata-Version: 2.4
Name: volvisualizer
Version: 1.2.4
Summary: Extract and visualize implied volatility from option data.
Home-page: https://github.com/GBERESEARCH/volvisualizer
Author: GBERESEARCH
Author-email: gberesearch@gmail.com
License: MIT
License-File: LICENSE
Requires-Dist: matplotlib>=3.0.3
Requires-Dist: plotly>=4.3.0
Requires-Dist: volvisdata>=1.0.1
Dynamic: license-file
